redorm/__init__.py
redorm/client.py
redorm/exceptions.py
redorm/model.py
redorm/relationships.py
redorm/settings.py
redorm/types.py
redorm-0.7.0.dist-info/WHEEL
redorm-0.7.0.dist-info/METADATA
redorm-0.7.0.dist-info/RECORD
